[
  {
    "pcmCompositeComponentId": "_DnM3YMS0EemNN6wcQsSNnA",
    "hardGoals": [
      {
        "name": "Anonymization service ensures the Authenticity of Anonymized data during the Downloading anonymized data",
        "serviceName": "Anonymization service",
        "functionalRequirement": {
          "assets": [
            {
              "pcmElementId": "_DnJNAMS0EemNN6wcQsSNnA",
              "name": "Anonymized data"
            }
          ],
          "pcmElementId": "_DnKbK8S0EemNN6wcQsSNnA",
          "name": "Downloading anonymized data"
        },
        "bbm": {
          "authenticity": true,
          "confidentiality": false,
          "integrity": true,
          "extraHg": "Signature Key Protection",
          "pcmElementId": "_DnRI38S0EemNN6wcQsSNnA",
          "name": "Digital Signature"
        },
        "SoftGoal": {
          "name": "Authenticity of Anonymized data",
          "concern": "authenticity",
          "asset": {
            "pcmElementId": "_DnJNAMS0EemNN6wcQsSNnA",
            "name": "Anonymized data"
          },
          "priority": true
        }
      },
      {
        "name": "Anonymization service ensures the Authenticity of Anonymized data during the Storing anonymized data",
        "serviceName": "Anonymization service",
        "functionalRequirement": {
          "assets": [
            {
              "pcmElementId": "_DnJNAMS0EemNN6wcQsSNnA",
              "name": "Anonymized data"
            }
          ],
          "pcmElementId": "_DnDtcMS0EemNN6wcQsSNnA",
          "name": "Storing anonymized data"
        },
        "bbm": {
          "authenticity": true,
          "confidentiality": false,
          "integrity": true,
          "extraHg": "Signature Key Protection",
          "pcmElementId": "_DnRI38S0EemNN6wcQsSNnA",
          "name": "Digital Signature"
        },
        "SoftGoal": {
          "name": "Authenticity of Anonymized data",
          "concern": "authenticity",
          "asset": {
            "pcmElementId": "_DnJNAMS0EemNN6wcQsSNnA",
            "name": "Anonymized data"
          },
          "priority": true
        }
      },
      {
        "name": "Anonymization service ensures the Authenticity of Anonymized data during the Storing data",
        "serviceName": "Anonymization service",
        "functionalRequirement": {
          "assets": [
            {
              "pcmElementId": "_DnJNAMS0EemNN6wcQsSNnA",
              "name": "Anonymized data"
            },
            {
              "pcmElementId": "_DnKbJsS0EemNN6wcQsSNnA",
              "name": "Data"
            }
          ],
          "pcmElementId": "_DnLCNMS0EemNN6wcQsSNnA",
          "name": "Storing data"
        },
        "bbm": {
          "authenticity": true,
          "confidentiality": false,
          "integrity": true,
          "extraHg": "Signature Key Protection",
          "pcmElementId": "_DnRI38S0EemNN6wcQsSNnA",
          "name": "Digital Signature"
        },
        "SoftGoal": {
          "name": "Authenticity of Anonymized data",
          "concern": "authenticity",
          "asset": {
            "pcmElementId": "_DnJNAMS0EemNN6wcQsSNnA",
            "name": "Anonymized data"
          },
          "priority": true
        }
      },
      {
        "name": "Anonymization service ensures the Authenticity of Crash cam operators\u0027 user accounts during the Authenticating crash cam operator",
        "serviceName": "Anonymization service",
        "functionalRequirement": {
          "assets": [
            {
              "pcmElementId": "_DnKbIsS0EemNN6wcQsSNnA",
              "name": "Crash cam operators user accounts"
            }
          ],
          "pcmElementId": "_DnLCMMS0EemNN6wcQsSNnA",
          "name": "Authenticating crash cam operator"
        },
        "bbm": {
          "authenticity": true,
          "confidentiality": false,
          "integrity": false,
          "extraHg": "User input is correctly checked or masked",
          "pcmElementId": "_DnRI58S0EemNN6wcQsSNnA",
          "name": "Password Authentication Scheme"
        },
        "SoftGoal": {
          "name": "Authenticity of Crash cam operators\u0027 user accounts",
          "concern": "authenticity",
          "asset": {
            "pcmElementId": "_DnKbIsS0EemNN6wcQsSNnA",
            "name": "Crash cam operators user accounts"
          },
          "priority": true
        }
      },
      {
        "name": "Anonymization service ensures the Authenticity of Data during the Explicitly granting access to raw data",
        "serviceName": "Anonymization service",
        "functionalRequirement": {
          "assets": [
            {
              "pcmElementId": "_DnKbJsS0EemNN6wcQsSNnA",
              "name": "Data"
            }
          ],
          "pcmElementId": "_DnKbJ8S0EemNN6wcQsSNnA",
          "name": "Explicitly granting access to raw data"
        },
        "bbm": {
          "authenticity": true,
          "confidentiality": false,
          "integrity": true,
          "pcmElementId": "_DnRI18S0EemNN6wcQsSNnA",
          "name": "Cryptographic Hash Function"
        },
        "SoftGoal": {
          "name": "Authenticity of Data",
          "concern": "authenticity",
          "asset": {
            "pcmElementId": "_DnKbJsS0EemNN6wcQsSNnA",
            "name": "Data"
          },
          "priority": true
        }
      },
      {
        "name": "Anonymization service ensures the Authenticity of Data during the Storing data",
        "serviceName": "Anonymization service",
        "functionalRequirement": {
          "assets": [
            {
              "pcmElementId": "_DnJNAMS0EemNN6wcQsSNnA",
              "name": "Anonymized data"
            },
            {
              "pcmElementId": "_DnKbJsS0EemNN6wcQsSNnA",
              "name": "Data"
            }
          ],
          "pcmElementId": "_DnLCNMS0EemNN6wcQsSNnA",
          "name": "Storing data"
        },
        "bbm": {
          "authenticity": true,
          "confidentiality": false,
          "integrity": true,
          "pcmElementId": "_DnRI18S0EemNN6wcQsSNnA",
          "name": "Cryptographic Hash Function"
        },
        "SoftGoal": {
          "name": "Authenticity of Data",
          "concern": "authenticity",
          "asset": {
            "pcmElementId": "_DnKbJsS0EemNN6wcQsSNnA",
            "name": "Data"
          },
          "priority": true
        }
      },
      {
        "name": "Anonymization service ensures the Authenticity of Privileged user account during the Authenticating prosecution authority",
        "serviceName": "Anonymization service",
        "functionalRequirement": {
          "assets": [
            {
              "pcmElementId": "_DnKbIsS0EemNN6wcQsSNnA",
              "name": "Crash cam operators user accounts"
            },
            {
              "pcmElementId": "_DnKbI8S0EemNN6wcQsSNnA",
              "name": "Privileged user account"
            }
          ],
          "pcmElementId": "_DnKbIMS0EemNN6wcQsSNnA",
          "name": "Authenticating prosecution authority"
        },
        "bbm": {
          "authenticity": true,
          "confidentiality": false,
          "integrity": false,
          "pcmElementId": "_DnRI08S0EemNN6wcQsSNnA",
          "name": "Asymmetric Crypto Authentication Scheme"
        },
        "SoftGoal": {
          "name": "Authenticity of Privileged user account",
          "concern": "authenticity",
          "asset": {
            "pcmElementId": "_DnKbI8S0EemNN6wcQsSNnA",
            "name": "Privileged user account"
          },
          "priority": true
        }
      },
      {
        "name": "Anonymization service ensures the Confidentiality of Crash cam operators\u0027 user accounts during the Authenticating crash cam operator",
        "serviceName": "Anonymization service",
        "functionalRequirement": {
          "assets": [
            {
              "pcmElementId": "_DnKbIsS0EemNN6wcQsSNnA",
              "name": "Crash cam operators user accounts"
            }
          ],
          "pcmElementId": "_DnLCMMS0EemNN6wcQsSNnA",
          "name": "Authenticating crash cam operator"
        },
        "bbm": {
          "authenticity": false,
          "confidentiality": true,
          "integrity": true,
          "pcmElementId": "_DnQhycS0EemNN6wcQsSNnA",
          "name": "Role-Based Access Control"
        },
        "SoftGoal": {
          "name": "Confidentiality of Crash cam operators\u0027 user accounts",
          "concern": "confidentiality",
          "asset": {
            "pcmElementId": "_DnKbIsS0EemNN6wcQsSNnA",
            "name": "Crash cam operators user accounts"
          },
          "priority": true
        }
      },
      {
        "name": "Anonymization service ensures the Confidentiality of Crash cam operators\u0027 user accounts during the Authenticating prosecution authority",
        "serviceName": "Anonymization service",
        "functionalRequirement": {
          "assets": [
            {
              "pcmElementId": "_DnKbIsS0EemNN6wcQsSNnA",
              "name": "Crash cam operators user accounts"
            },
            {
              "pcmElementId": "_DnKbI8S0EemNN6wcQsSNnA",
              "name": "Privileged user account"
            }
          ],
          "pcmElementId": "_DnKbIMS0EemNN6wcQsSNnA",
          "name": "Authenticating prosecution authority"
        },
        "bbm": {
          "authenticity": false,
          "confidentiality": true,
          "integrity": true,
          "pcmElementId": "_DnQhycS0EemNN6wcQsSNnA",
          "name": "Role-Based Access Control"
        },
        "SoftGoal": {
          "name": "Confidentiality of Crash cam operators\u0027 user accounts",
          "concern": "confidentiality",
          "asset": {
            "pcmElementId": "_DnKbIsS0EemNN6wcQsSNnA",
            "name": "Crash cam operators user accounts"
          },
          "priority": true
        }
      },
      {
        "name": "Anonymization service ensures the Confidentiality of Data during the Explicitly granting access to raw data",
        "serviceName": "Anonymization service",
        "functionalRequirement": {
          "assets": [
            {
              "pcmElementId": "_DnKbJsS0EemNN6wcQsSNnA",
              "name": "Data"
            }
          ],
          "pcmElementId": "_DnKbJ8S0EemNN6wcQsSNnA",
          "name": "Explicitly granting access to raw data"
        },
        "bbm": {
          "authenticity": false,
          "confidentiality": true,
          "integrity": true,
          "pcmElementId": "_DnQhycS0EemNN6wcQsSNnA",
          "name": "Role-Based Access Control"
        },
        "SoftGoal": {
          "name": "Confidentiality of Data",
          "concern": "confidentiality",
          "asset": {
            "pcmElementId": "_DnKbJsS0EemNN6wcQsSNnA",
            "name": "Data"
          },
          "priority": true
        }
      },
      {
        "name": "Anonymization service ensures the Confidentiality of Data during the Storing data",
        "serviceName": "Anonymization service",
        "functionalRequirement": {
          "assets": [
            {
              "pcmElementId": "_DnJNAMS0EemNN6wcQsSNnA",
              "name": "Anonymized data"
            },
            {
              "pcmElementId": "_DnKbJsS0EemNN6wcQsSNnA",
              "name": "Data"
            }
          ],
          "pcmElementId": "_DnLCNMS0EemNN6wcQsSNnA",
          "name": "Storing data"
        },
        "bbm": {
          "authenticity": false,
          "confidentiality": true,
          "integrity": true,
          "extraHg": "Private Key Protection",
          "pcmElementId": "_DnRI28S0EemNN6wcQsSNnA",
          "name": "Hybrid Encryption"
        },
        "SoftGoal": {
          "name": "Confidentiality of Data",
          "concern": "confidentiality",
          "asset": {
            "pcmElementId": "_DnKbJsS0EemNN6wcQsSNnA",
            "name": "Data"
          },
          "priority": true
        }
      },
      {
        "name": "Anonymization service ensures the Confidentiality of Privileged user account during the Authenticating prosecution authority",
        "serviceName": "Anonymization service",
        "functionalRequirement": {
          "assets": [
            {
              "pcmElementId": "_DnKbIsS0EemNN6wcQsSNnA",
              "name": "Crash cam operators user accounts"
            },
            {
              "pcmElementId": "_DnKbI8S0EemNN6wcQsSNnA",
              "name": "Privileged user account"
            }
          ],
          "pcmElementId": "_DnKbIMS0EemNN6wcQsSNnA",
          "name": "Authenticating prosecution authority"
        },
        "bbm": {
          "authenticity": false,
          "confidentiality": true,
          "integrity": true,
          "pcmElementId": "_DnQhycS0EemNN6wcQsSNnA",
          "name": "Role-Based Access Control"
        },
        "SoftGoal": {
          "name": "Confidentiality of Privileged user account",
          "concern": "confidentiality",
          "asset": {
            "pcmElementId": "_DnKbI8S0EemNN6wcQsSNnA",
            "name": "Privileged user account"
          },
          "priority": true
        }
      },
      {
        "name": "Anonymization service ensures the Integrity of Anonymized data during the Anonymizing data",
        "serviceName": "Anonymization service",
        "functionalRequirement": {
          "assets": [
            {
              "pcmElementId": "_DnJNAMS0EemNN6wcQsSNnA",
              "name": "Anonymized data"
            }
          ],
          "pcmElementId": "_DnKbKcS0EemNN6wcQsSNnA",
          "name": "Anonymizing data"
        },
        "bbm": {
          "authenticity": true,
          "confidentiality": false,
          "integrity": true,
          "extraHg": "Signature Key Protection",
          "pcmElementId": "_DnRI38S0EemNN6wcQsSNnA",
          "name": "Digital Signature"
        },
        "SoftGoal": {
          "name": "Integrity of Anonymized data",
          "concern": "integrity",
          "asset": {
            "pcmElementId": "_DnJNAMS0EemNN6wcQsSNnA",
            "name": "Anonymized data"
          },
          "priority": true
        }
      },
      {
        "name": "Anonymization service ensures the Integrity of Anonymized data during the Downloading anonymized data",
        "serviceName": "Anonymization service",
        "functionalRequirement": {
          "assets": [
            {
              "pcmElementId": "_DnJNAMS0EemNN6wcQsSNnA",
              "name": "Anonymized data"
            }
          ],
          "pcmElementId": "_DnKbK8S0EemNN6wcQsSNnA",
          "name": "Downloading anonymized data"
        },
        "bbm": {
          "authenticity": true,
          "confidentiality": false,
          "integrity": true,
          "extraHg": "Signature Key Protection",
          "pcmElementId": "_DnRI38S0EemNN6wcQsSNnA",
          "name": "Digital Signature"
        },
        "SoftGoal": {
          "name": "Integrity of Anonymized data",
          "concern": "integrity",
          "asset": {
            "pcmElementId": "_DnJNAMS0EemNN6wcQsSNnA",
            "name": "Anonymized data"
          },
          "priority": true
        }
      },
      {
        "name": "Anonymization service ensures the Integrity of Anonymized data during the Storing anonymized data",
        "serviceName": "Anonymization service",
        "functionalRequirement": {
          "assets": [
            {
              "pcmElementId": "_DnJNAMS0EemNN6wcQsSNnA",
              "name": "Anonymized data"
            }
          ],
          "pcmElementId": "_DnDtcMS0EemNN6wcQsSNnA",
          "name": "Storing anonymized data"
        },
        "bbm": {
          "authenticity": true,
          "confidentiality": false,
          "integrity": true,
          "extraHg": "Signature Key Protection",
          "pcmElementId": "_DnRI38S0EemNN6wcQsSNnA",
          "name": "Digital Signature"
        },
        "SoftGoal": {
          "name": "Integrity of Anonymized data",
          "concern": "integrity",
          "asset": {
            "pcmElementId": "_DnJNAMS0EemNN6wcQsSNnA",
            "name": "Anonymized data"
          },
          "priority": true
        }
      },
      {
        "name": "Anonymization service ensures the Integrity of Anonymized data during the Storing data",
        "serviceName": "Anonymization service",
        "functionalRequirement": {
          "assets": [
            {
              "pcmElementId": "_DnJNAMS0EemNN6wcQsSNnA",
              "name": "Anonymized data"
            },
            {
              "pcmElementId": "_DnKbJsS0EemNN6wcQsSNnA",
              "name": "Data"
            }
          ],
          "pcmElementId": "_DnLCNMS0EemNN6wcQsSNnA",
          "name": "Storing data"
        },
        "bbm": {
          "authenticity": true,
          "confidentiality": false,
          "integrity": true,
          "extraHg": "Signature Key Protection",
          "pcmElementId": "_DnRI38S0EemNN6wcQsSNnA",
          "name": "Digital Signature"
        },
        "SoftGoal": {
          "name": "Integrity of Anonymized data",
          "concern": "integrity",
          "asset": {
            "pcmElementId": "_DnJNAMS0EemNN6wcQsSNnA",
            "name": "Anonymized data"
          },
          "priority": true
        }
      },
      {
        "name": "Anonymization service ensures the Integrity of Crash cam operators\u0027 user accounts during the Authenticating crash cam operator",
        "serviceName": "Anonymization service",
        "functionalRequirement": {
          "assets": [
            {
              "pcmElementId": "_DnKbIsS0EemNN6wcQsSNnA",
              "name": "Crash cam operators user accounts"
            }
          ],
          "pcmElementId": "_DnLCMMS0EemNN6wcQsSNnA",
          "name": "Authenticating crash cam operator"
        },
        "bbm": {
          "authenticity": false,
          "confidentiality": true,
          "integrity": true,
          "pcmElementId": "_DnQhycS0EemNN6wcQsSNnA",
          "name": "Role-Based Access Control"
        },
        "SoftGoal": {
          "name": "Integrity of Crash cam operators\u0027 user accounts",
          "concern": "integrity",
          "asset": {
            "pcmElementId": "_DnKbIsS0EemNN6wcQsSNnA",
            "name": "Crash cam operators user accounts"
          },
          "priority": true
        }
      },
      {
        "name": "Anonymization service ensures the Integrity of Crash cam operators\u0027 user accounts during the Authenticating prosecution authority",
        "serviceName": "Anonymization service",
        "functionalRequirement": {
          "assets": [
            {
              "pcmElementId": "_DnKbIsS0EemNN6wcQsSNnA",
              "name": "Crash cam operators user accounts"
            },
            {
              "pcmElementId": "_DnKbI8S0EemNN6wcQsSNnA",
              "name": "Privileged user account"
            }
          ],
          "pcmElementId": "_DnKbIMS0EemNN6wcQsSNnA",
          "name": "Authenticating prosecution authority"
        },
        "bbm": {
          "authenticity": false,
          "confidentiality": true,
          "integrity": true,
          "pcmElementId": "_DnQhycS0EemNN6wcQsSNnA",
          "name": "Role-Based Access Control"
        },
        "SoftGoal": {
          "name": "Integrity of Crash cam operators\u0027 user accounts",
          "concern": "integrity",
          "asset": {
            "pcmElementId": "_DnKbIsS0EemNN6wcQsSNnA",
            "name": "Crash cam operators user accounts"
          },
          "priority": true
        }
      },
      {
        "name": "Anonymization service ensures the Integrity of Data during the Explicitly granting access to raw data",
        "serviceName": "Anonymization service",
        "functionalRequirement": {
          "assets": [
            {
              "pcmElementId": "_DnKbJsS0EemNN6wcQsSNnA",
              "name": "Data"
            }
          ],
          "pcmElementId": "_DnKbJ8S0EemNN6wcQsSNnA",
          "name": "Explicitly granting access to raw data"
        },
        "bbm": {
          "authenticity": true,
          "confidentiality": false,
          "integrity": true,
          "pcmElementId": "_DnRI18S0EemNN6wcQsSNnA",
          "name": "Cryptographic Hash Function"
        },
        "SoftGoal": {
          "name": "Integrity of Data",
          "concern": "integrity",
          "asset": {
            "pcmElementId": "_DnKbJsS0EemNN6wcQsSNnA",
            "name": "Data"
          },
          "priority": true
        }
      },
      {
        "name": "Anonymization service ensures the Integrity of Data during the Storing data",
        "serviceName": "Anonymization service",
        "functionalRequirement": {
          "assets": [
            {
              "pcmElementId": "_DnJNAMS0EemNN6wcQsSNnA",
              "name": "Anonymized data"
            },
            {
              "pcmElementId": "_DnKbJsS0EemNN6wcQsSNnA",
              "name": "Data"
            }
          ],
          "pcmElementId": "_DnLCNMS0EemNN6wcQsSNnA",
          "name": "Storing data"
        },
        "bbm": {
          "authenticity": false,
          "confidentiality": true,
          "integrity": true,
          "extraHg": "Private Key Protection",
          "pcmElementId": "_DnRI28S0EemNN6wcQsSNnA",
          "name": "Hybrid Encryption"
        },
        "SoftGoal": {
          "name": "Integrity of Data",
          "concern": "integrity",
          "asset": {
            "pcmElementId": "_DnKbJsS0EemNN6wcQsSNnA",
            "name": "Data"
          },
          "priority": true
        }
      }
    ],
    "blackBoxMechanisms": [
      {
        "authenticity": false,
        "confidentiality": true,
        "integrity": true,
        "pcmElementId": "_DnQhycS0EemNN6wcQsSNnA",
        "name": "Role-Based Access Control"
      },
      {
        "authenticity": true,
        "confidentiality": false,
        "integrity": true,
        "pcmElementId": "_DnRI18S0EemNN6wcQsSNnA",
        "name": "Cryptographic Hash Function"
      },
      {
        "authenticity": true,
        "confidentiality": false,
        "integrity": false,
        "pcmElementId": "_DnRI08S0EemNN6wcQsSNnA",
        "name": "Asymmetric Crypto Authentication Scheme"
      },
      {
        "authenticity": false,
        "confidentiality": true,
        "integrity": true,
        "extraHg": "Private Key Protection",
        "pcmElementId": "_DnRI28S0EemNN6wcQsSNnA",
        "name": "Hybrid Encryption"
      },
      {
        "authenticity": true,
        "confidentiality": false,
        "integrity": true,
        "extraHg": "Signature Key Protection",
        "pcmElementId": "_DnRI38S0EemNN6wcQsSNnA",
        "name": "Digital Signature"
      },
      {
        "authenticity": true,
        "confidentiality": false,
        "integrity": false,
        "extraHg": "User input is correctly checked or masked",
        "pcmElementId": "_DnRI58S0EemNN6wcQsSNnA",
        "name": "Password Authentication Scheme"
      }
    ],
    "providedFunctionalRequirements": [
      {
        "assets": [
          {
            "pcmElementId": "_DnKbIsS0EemNN6wcQsSNnA",
            "name": "Crash cam operators user accounts"
          },
          {
            "pcmElementId": "_DnKbI8S0EemNN6wcQsSNnA",
            "name": "Privileged user account"
          }
        ],
        "pcmElementId": "_DnKbIMS0EemNN6wcQsSNnA",
        "name": "Authenticating prosecution authority"
      },
      {
        "assets": [
          {
            "pcmElementId": "_DnJNAMS0EemNN6wcQsSNnA",
            "name": "Anonymized data"
          }
        ],
        "pcmElementId": "_DnDtcMS0EemNN6wcQsSNnA",
        "name": "Storing anonymized data"
      },
      {
        "assets": [
          {
            "pcmElementId": "_DnKbJsS0EemNN6wcQsSNnA",
            "name": "Data"
          }
        ],
        "pcmElementId": "_DnKbJ8S0EemNN6wcQsSNnA",
        "name": "Explicitly granting access to raw data"
      },
      {
        "assets": [
          {
            "pcmElementId": "_DnJNAMS0EemNN6wcQsSNnA",
            "name": "Anonymized data"
          }
        ],
        "pcmElementId": "_DnKbKcS0EemNN6wcQsSNnA",
        "name": "Anonymizing data"
      },
      {
        "assets": [
          {
            "pcmElementId": "_DnJNAMS0EemNN6wcQsSNnA",
            "name": "Anonymized data"
          }
        ],
        "pcmElementId": "_DnKbK8S0EemNN6wcQsSNnA",
        "name": "Downloading anonymized data"
      },
      {
        "assets": [
          {
            "pcmElementId": "_DnKbIsS0EemNN6wcQsSNnA",
            "name": "Crash cam operators user accounts"
          }
        ],
        "pcmElementId": "_DnLCMMS0EemNN6wcQsSNnA",
        "name": "Authenticating crash cam operator"
      },
      {
        "assets": [
          {
            "pcmElementId": "_DnJNAMS0EemNN6wcQsSNnA",
            "name": "Anonymized data"
          },
          {
            "pcmElementId": "_DnKbJsS0EemNN6wcQsSNnA",
            "name": "Data"
          }
        ],
        "pcmElementId": "_DnLCNMS0EemNN6wcQsSNnA",
        "name": "Storing data"
      }
    ],
    "pcmElementId": "_DnOskMS0EemNN6wcQsSNnA",
    "name": "Anonymization service"
  },
  {
    "pcmCompositeComponentId": "_DnP6sMS0EemNN6wcQsSNnA",
    "hardGoals": [
      {
        "name": "Crash cam app ensures the Authenticity of Data during the Recording data",
        "serviceName": "Crash cam app",
        "functionalRequirement": {
          "assets": [
            {
              "pcmElementId": "_DnKbJsS0EemNN6wcQsSNnA",
              "name": "Data"
            }
          ],
          "pcmElementId": "_DnLCMsS0EemNN6wcQsSNnA",
          "name": "Recording data"
        },
        "bbm": {
          "authenticity": true,
          "confidentiality": false,
          "integrity": true,
          "pcmElementId": "_DnRI18S0EemNN6wcQsSNnA",
          "name": "Cryptographic Hash Function"
        },
        "SoftGoal": {
          "name": "Authenticity of Data",
          "concern": "authenticity",
          "asset": {
            "pcmElementId": "_DnKbJsS0EemNN6wcQsSNnA",
            "name": "Data"
          },
          "priority": true
        }
      },
      {
        "name": "Crash cam app ensures the Authenticity of Data during the Uploading data",
        "serviceName": "Crash cam app",
        "functionalRequirement": {
          "assets": [
            {
              "pcmElementId": "_DnKbJsS0EemNN6wcQsSNnA",
              "name": "Data"
            }
          ],
          "pcmElementId": "_DnKbJMS0EemNN6wcQsSNnA",
          "name": "Uploading data"
        },
        "bbm": {
          "authenticity": true,
          "confidentiality": false,
          "integrity": true,
          "pcmElementId": "_DnRI18S0EemNN6wcQsSNnA",
          "name": "Cryptographic Hash Function"
        },
        "SoftGoal": {
          "name": "Authenticity of Data",
          "concern": "authenticity",
          "asset": {
            "pcmElementId": "_DnKbJsS0EemNN6wcQsSNnA",
            "name": "Data"
          },
          "priority": true
        }
      },
      {
        "name": "Crash cam app ensures the Confidentiality of Crash cam operators\u0027 user accounts during the Authenticating crash cam operator",
        "serviceName": "Crash cam app",
        "functionalRequirement": {
          "assets": [
            {
              "pcmElementId": "_DnKbIsS0EemNN6wcQsSNnA",
              "name": "Crash cam operators user accounts"
            }
          ],
          "pcmElementId": "_DnLCMMS0EemNN6wcQsSNnA",
          "name": "Authenticating crash cam operator"
        },
        "bbm": {
          "authenticity": false,
          "confidentiality": true,
          "integrity": true,
          "pcmElementId": "_DnQhwcS0EemNN6wcQsSNnA",
          "name": "Access Control"
        },
        "SoftGoal": {
          "name": "Confidentiality of Crash cam operators\u0027 user accounts",
          "concern": "confidentiality",
          "asset": {
            "pcmElementId": "_DnKbIsS0EemNN6wcQsSNnA",
            "name": "Crash cam operators user accounts"
          },
          "priority": true
        }
      },
      {
        "name": "Crash cam app ensures the Confidentiality of Data during the Recording data",
        "serviceName": "Crash cam app",
        "functionalRequirement": {
          "assets": [
            {
              "pcmElementId": "_DnKbJsS0EemNN6wcQsSNnA",
              "name": "Data"
            }
          ],
          "pcmElementId": "_DnLCMsS0EemNN6wcQsSNnA",
          "name": "Recording data"
        },
        "bbm": {
          "authenticity": false,
          "confidentiality": true,
          "integrity": true,
          "extraHg": "Private Key Protection",
          "pcmElementId": "_DnRI28S0EemNN6wcQsSNnA",
          "name": "Hybrid Encryption"
        },
        "SoftGoal": {
          "name": "Confidentiality of Data",
          "concern": "confidentiality",
          "asset": {
            "pcmElementId": "_DnKbJsS0EemNN6wcQsSNnA",
            "name": "Data"
          },
          "priority": true
        }
      },
      {
        "name": "Crash cam app ensures the Confidentiality of Data during the Storing data",
        "serviceName": "Crash cam app",
        "functionalRequirement": {
          "assets": [
            {
              "pcmElementId": "_DnJNAMS0EemNN6wcQsSNnA",
              "name": "Anonymized data"
            },
            {
              "pcmElementId": "_DnKbJsS0EemNN6wcQsSNnA",
              "name": "Data"
            }
          ],
          "pcmElementId": "_DnLCNMS0EemNN6wcQsSNnA",
          "name": "Storing data"
        },
        "bbm": {
          "authenticity": false,
          "confidentiality": true,
          "integrity": true,
          "extraHg": "Private Key Protection",
          "pcmElementId": "_DnRI28S0EemNN6wcQsSNnA",
          "name": "Hybrid Encryption"
        },
        "SoftGoal": {
          "name": "Confidentiality of Data",
          "concern": "confidentiality",
          "asset": {
            "pcmElementId": "_DnKbJsS0EemNN6wcQsSNnA",
            "name": "Data"
          },
          "priority": true
        }
      },
      {
        "name": "Crash cam app ensures the Confidentiality of Data during the Uploading data",
        "serviceName": "Crash cam app",
        "functionalRequirement": {
          "assets": [
            {
              "pcmElementId": "_DnKbJsS0EemNN6wcQsSNnA",
              "name": "Data"
            }
          ],
          "pcmElementId": "_DnKbJMS0EemNN6wcQsSNnA",
          "name": "Uploading data"
        },
        "bbm": {
          "authenticity": false,
          "confidentiality": true,
          "integrity": true,
          "extraHg": "Private Key Protection",
          "pcmElementId": "_DnRI28S0EemNN6wcQsSNnA",
          "name": "Hybrid Encryption"
        },
        "SoftGoal": {
          "name": "Confidentiality of Data",
          "concern": "confidentiality",
          "asset": {
            "pcmElementId": "_DnKbJsS0EemNN6wcQsSNnA",
            "name": "Data"
          },
          "priority": true
        }
      },
      {
        "name": "Crash cam app ensures the Integrity of Crash cam operators\u0027 user accounts during the Authenticating crash cam operator",
        "serviceName": "Crash cam app",
        "functionalRequirement": {
          "assets": [
            {
              "pcmElementId": "_DnKbIsS0EemNN6wcQsSNnA",
              "name": "Crash cam operators user accounts"
            }
          ],
          "pcmElementId": "_DnLCMMS0EemNN6wcQsSNnA",
          "name": "Authenticating crash cam operator"
        },
        "bbm": {
          "authenticity": false,
          "confidentiality": true,
          "integrity": true,
          "pcmElementId": "_DnQhwcS0EemNN6wcQsSNnA",
          "name": "Access Control"
        },
        "SoftGoal": {
          "name": "Integrity of Crash cam operators\u0027 user accounts",
          "concern": "integrity",
          "asset": {
            "pcmElementId": "_DnKbIsS0EemNN6wcQsSNnA",
            "name": "Crash cam operators user accounts"
          },
          "priority": true
        }
      },
      {
        "name": "Crash cam app ensures the Integrity of Data during the Recording data",
        "serviceName": "Crash cam app",
        "functionalRequirement": {
          "assets": [
            {
              "pcmElementId": "_DnKbJsS0EemNN6wcQsSNnA",
              "name": "Data"
            }
          ],
          "pcmElementId": "_DnLCMsS0EemNN6wcQsSNnA",
          "name": "Recording data"
        },
        "bbm": {
          "authenticity": true,
          "confidentiality": false,
          "integrity": true,
          "pcmElementId": "_DnRI18S0EemNN6wcQsSNnA",
          "name": "Cryptographic Hash Function"
        },
        "SoftGoal": {
          "name": "Integrity of Data",
          "concern": "integrity",
          "asset": {
            "pcmElementId": "_DnKbJsS0EemNN6wcQsSNnA",
            "name": "Data"
          },
          "priority": true
        }
      },
      {
        "name": "Crash cam app ensures the Integrity of Data during the Uploading data",
        "serviceName": "Crash cam app",
        "functionalRequirement": {
          "assets": [
            {
              "pcmElementId": "_DnKbJsS0EemNN6wcQsSNnA",
              "name": "Data"
            }
          ],
          "pcmElementId": "_DnKbJMS0EemNN6wcQsSNnA",
          "name": "Uploading data"
        },
        "bbm": {
          "authenticity": true,
          "confidentiality": false,
          "integrity": true,
          "pcmElementId": "_DnRI18S0EemNN6wcQsSNnA",
          "name": "Cryptographic Hash Function"
        },
        "SoftGoal": {
          "name": "Integrity of Data",
          "concern": "integrity",
          "asset": {
            "pcmElementId": "_DnKbJsS0EemNN6wcQsSNnA",
            "name": "Data"
          },
          "priority": true
        }
      }
    ],
    "blackBoxMechanisms": [
      {
        "authenticity": false,
        "confidentiality": true,
        "integrity": true,
        "pcmElementId": "_DnQhwcS0EemNN6wcQsSNnA",
        "name": "Access Control"
      },
      {
        "authenticity": true,
        "confidentiality": false,
        "integrity": true,
        "pcmElementId": "_DnRI18S0EemNN6wcQsSNnA",
        "name": "Cryptographic Hash Function"
      },
      {
        "authenticity": false,
        "confidentiality": true,
        "integrity": true,
        "extraHg": "Private Key Protection",
        "pcmElementId": "_DnRI28S0EemNN6wcQsSNnA",
        "name": "Hybrid Encryption"
      }
    ],
    "providedFunctionalRequirements": [
      {
        "assets": [
          {
            "pcmElementId": "_DnKbJsS0EemNN6wcQsSNnA",
            "name": "Data"
          }
        ],
        "pcmElementId": "_DnKbJMS0EemNN6wcQsSNnA",
        "name": "Uploading data"
      },
      {
        "assets": [
          {
            "pcmElementId": "_DnKbIsS0EemNN6wcQsSNnA",
            "name": "Crash cam operators user accounts"
          }
        ],
        "pcmElementId": "_DnLCMMS0EemNN6wcQsSNnA",
        "name": "Authenticating crash cam operator"
      },
      {
        "assets": [
          {
            "pcmElementId": "_DnKbJsS0EemNN6wcQsSNnA",
            "name": "Data"
          }
        ],
        "pcmElementId": "_DnLCMsS0EemNN6wcQsSNnA",
        "name": "Recording data"
      },
      {
        "assets": [
          {
            "pcmElementId": "_DnJNAMS0EemNN6wcQsSNnA",
            "name": "Anonymized data"
          },
          {
            "pcmElementId": "_DnKbJsS0EemNN6wcQsSNnA",
            "name": "Data"
          }
        ],
        "pcmElementId": "_DnLCNMS0EemNN6wcQsSNnA",
        "name": "Storing data"
      }
    ],
    "pcmElementId": "_DnP6scS0EemNN6wcQsSNnA",
    "name": "Crash cam app"
  }
]